clip.py
clip.py-0.3.2.dist-info/top_level.txt
clip.py-0.3.2.dist-info/RECORD
clip.py-0.3.2.dist-info/WHEEL
clip.py-0.3.2.dist-info/metadata.json
clip.py-0.3.2.dist-info/METADATA
clip.py-0.3.2.dist-info/DESCRIPTION.rst
