Metadata-Version: 2.0
Name: clip.py
Version: 0.3.2
Summary: Embeddable, composable command line interface parsing
Home-page: https://github.com/willyg302/clip.py
Author: William Gaul
Author-email: willyg302@gmail.com
License: MIT
Platform: any
Classifier: License :: OSI Approved :: MIT License
Classifier: Programming Language :: Python :: 2.7
Classifier: Programming Language :: Python :: 3.4
